pyefergy/__init__.py
pyefergy/exceptions.py
pyefergy/py.typed
tests/__init__.py
tests/conftest.py
tests/test_init.py
pyefergy-22.1.1.dist-info/LICENSE
pyefergy-22.1.1.dist-info/METADATA
pyefergy-22.1.1.dist-info/WHEEL
pyefergy-22.1.1.dist-info/top_level.txt
pyefergy-22.1.1.dist-info/RECORD
