Metadata-Version: 2.1
Name: pyefergy
Version: 22.1.1
Summary: An API library for Efergy energy meters.
Home-page: https://github.com/tkdrob/pyefergy
Author: Robert Hillis
Author-email: tkdrob4390@yahoo.com
License: UNKNOWN
Platform: UNKNOWN
Classifier: Programming Language :: Python :: 3
Classifier: License :: OSI Approved :: MIT License
Classifier: Operating System :: OS Independent
Requires-Python: >=3.8
License-File: LICENSE
Requires-Dist: aiohttp (>=3.4.4)
Requires-Dist: iso4217 (>=1.2.20150619)
Requires-Dist: pytz
